LICENSE
README.md
requirements.txt
setup.py
jam_gpt/__init__.py
jam_gpt/config.py
jam_gpt/data.py
jam_gpt/lm.py
jam_gpt/model.py
jam_gpt/tokenizer.py
jam_gpt.egg-info/PKG-INFO
jam_gpt.egg-info/SOURCES.txt
jam_gpt.egg-info/dependency_links.txt
jam_gpt.egg-info/requires.txt
jam_gpt.egg-info/top_level.txt